{
    "resourceType": "OperationDefinition",
    "id": "lookup",
    "url": "[base]/OperationDefinition/lookup",
    "version": "1.0.0",
    "name": "lookup",
    "status": "active",
    "kind": "operation",
    "description": "lookup a code from codesystem",
    "code": "lookup",
    "system": true,
    "type": false,
    "instance": false,
    "parameter": [
        {
            "name": "_outputFormat",
            "use": "in",
            "min": 0,
            "max": "1",
            "documentation": "The format for the requested bulk data files to be generated. Supported formats - `application/fhir+ndjson`.",
            "type": "string"
        },
    ]
}
