{
  "resourceType": "Bundle",
  "type": "batch",
  "entry": [
    {
      "resource": {
        "resourceType": "Observation",
        "id": "intervention-bp-01",
        "status": "final",
        "code": {"coding": [{"system": "http://loinc.org", "code": "85354-9", "display": "Blood pressure panel"}]},
        "subject": {"reference": "Patient/crisis-pt-01"},
        "effectiveDateTime": "2026-03-30T14:00:00Z",
        "component": [
          {"code": {"coding": [{"system": "http://loinc.org", "code": "8480-6", "display": "Systolic BP"}]}, "valueQuantity": {"value": 128, "unit": "mmHg", "system": "http://unitsofmeasure.org", "code": "mm[Hg]"}},
          {"code": {"coding": [{"system": "http://loinc.org", "code": "8462-4", "display": "Diastolic BP"}]}, "valueQuantity": {"value": 82, "unit": "mmHg", "system": "http://unitsofmeasure.org", "code": "mm[Hg]"}}
        ]
      },
      "request": {"method": "PUT", "url": "Observation/intervention-bp-01"}
    },
    {
      "resource": {
        "resourceType": "Observation",
        "id": "intervention-bp-02",
        "status": "final",
        "code": {"coding": [{"system": "http://loinc.org", "code": "85354-9", "display": "Blood pressure panel"}]},
        "subject": {"reference": "Patient/crisis-pt-02"},
        "effectiveDateTime": "2026-03-30T14:15:00Z",
        "component": [
          {"code": {"coding": [{"system": "http://loinc.org", "code": "8480-6", "display": "Systolic BP"}]}, "valueQuantity": {"value": 132, "unit": "mmHg", "system": "http://unitsofmeasure.org", "code": "mm[Hg]"}},
          {"code": {"coding": [{"system": "http://loinc.org", "code": "8462-4", "display": "Diastolic BP"}]}, "valueQuantity": {"value": 85, "unit": "mmHg", "system": "http://unitsofmeasure.org", "code": "mm[Hg]"}}
        ]
      },
      "request": {"method": "PUT", "url": "Observation/intervention-bp-02"}
    },
    {
      "resource": {
        "resourceType": "Observation",
        "id": "intervention-bp-03",
        "status": "final",
        "code": {"coding": [{"system": "http://loinc.org", "code": "85354-9", "display": "Blood pressure panel"}]},
        "subject": {"reference": "Patient/crisis-pt-03"},
        "effectiveDateTime": "2026-03-30T14:30:00Z",
        "component": [
          {"code": {"coding": [{"system": "http://loinc.org", "code": "8480-6", "display": "Systolic BP"}]}, "valueQuantity": {"value": 125, "unit": "mmHg", "system": "http://unitsofmeasure.org", "code": "mm[Hg]"}},
          {"code": {"coding": [{"system": "http://loinc.org", "code": "8462-4", "display": "Diastolic BP"}]}, "valueQuantity": {"value": 78, "unit": "mmHg", "system": "http://unitsofmeasure.org", "code": "mm[Hg]"}}
        ]
      },
      "request": {"method": "PUT", "url": "Observation/intervention-bp-03"}
    },
    {
      "resource": {
        "resourceType": "Observation",
        "id": "intervention-bp-05",
        "status": "final",
        "code": {"coding": [{"system": "http://loinc.org", "code": "85354-9", "display": "Blood pressure panel"}]},
        "subject": {"reference": "Patient/crisis-pt-05"},
        "effectiveDateTime": "2026-03-30T15:00:00Z",
        "component": [
          {"code": {"coding": [{"system": "http://loinc.org", "code": "8480-6", "display": "Systolic BP"}]}, "valueQuantity": {"value": 135, "unit": "mmHg", "system": "http://unitsofmeasure.org", "code": "mm[Hg]"}},
          {"code": {"coding": [{"system": "http://loinc.org", "code": "8462-4", "display": "Diastolic BP"}]}, "valueQuantity": {"value": 86, "unit": "mmHg", "system": "http://unitsofmeasure.org", "code": "mm[Hg]"}}
        ]
      },
      "request": {"method": "PUT", "url": "Observation/intervention-bp-05"}
    },
    {
      "resource": {
        "resourceType": "Observation",
        "id": "intervention-bp-07",
        "status": "final",
        "code": {"coding": [{"system": "http://loinc.org", "code": "85354-9", "display": "Blood pressure panel"}]},
        "subject": {"reference": "Patient/crisis-pt-07"},
        "effectiveDateTime": "2026-03-30T15:30:00Z",
        "component": [
          {"code": {"coding": [{"system": "http://loinc.org", "code": "8480-6", "display": "Systolic BP"}]}, "valueQuantity": {"value": 130, "unit": "mmHg", "system": "http://unitsofmeasure.org", "code": "mm[Hg]"}},
          {"code": {"coding": [{"system": "http://loinc.org", "code": "8462-4", "display": "Diastolic BP"}]}, "valueQuantity": {"value": 80, "unit": "mmHg", "system": "http://unitsofmeasure.org", "code": "mm[Hg]"}}
        ]
      },
      "request": {"method": "PUT", "url": "Observation/intervention-bp-07"}
    },
    {
      "resource": {
        "resourceType": "Observation",
        "id": "intervention-bp-09",
        "status": "final",
        "code": {"coding": [{"system": "http://loinc.org", "code": "85354-9", "display": "Blood pressure panel"}]},
        "subject": {"reference": "Patient/crisis-pt-09"},
        "effectiveDateTime": "2026-03-30T16:00:00Z",
        "component": [
          {"code": {"coding": [{"system": "http://loinc.org", "code": "8480-6", "display": "Systolic BP"}]}, "valueQuantity": {"value": 122, "unit": "mmHg", "system": "http://unitsofmeasure.org", "code": "mm[Hg]"}},
          {"code": {"coding": [{"system": "http://loinc.org", "code": "8462-4", "display": "Diastolic BP"}]}, "valueQuantity": {"value": 76, "unit": "mmHg", "system": "http://unitsofmeasure.org", "code": "mm[Hg]"}}
        ]
      },
      "request": {"method": "PUT", "url": "Observation/intervention-bp-09"}
    }
  ]
}
